{"cameraMode":{"drawMode":0,"name":"Shaded","section":"Shading Mode"},"sceneLighting":true,"audioPlay":false,"sceneViewState":{"m_AlwaysRefresh":false,"showFog":true,"showSkybox":true,"showFlares":true,"showImageEffects":true,"showParticleSystems":true,"showVisualEffectGraphs":true,"m_FxEnabled":true},"in2DMode":false,"pivot":{"x":-19.699710845947267,"y":5.5134477615356449,"z":-21.956912994384767},"rotation":{"x":-0.24647113680839539,"y":0.7462841868400574,"z":-0.3733881115913391,"w":-0.4930292069911957},"size":6.084661483764648,"orthographic":false}